fonolo/__init__.py
fonolo/client.py
fonolo/api/__init__.py
fonolo/api/call.py
fonolo/api/callback.py
fonolo/api/calls.py
fonolo/api/option.py
fonolo/api/options.py
fonolo/api/profile.py
fonolo/api/profiles.py
fonolo/api/question.py
fonolo/api/questions.py
fonolo/api/realtime.py
fonolo/api/requesthandler.py
fonolo/api/schedule.py
fonolo/api/scheduled.py
fonolo/api/scheduling.py
fonolo/api/timezones.py
fonolo/exception/__init__.py
fonolo/exception/exception.py
fonolo-1.0.1.dist-info/LICENSE
fonolo-1.0.1.dist-info/METADATA
fonolo-1.0.1.dist-info/WHEEL
fonolo-1.0.1.dist-info/top_level.txt
fonolo-1.0.1.dist-info/RECORD
